bearish/__init__.py
bearish-0.1.1.dist-info/METADATA
bearish-0.1.1.dist-info/WHEEL
bearish-0.1.1.dist-info/RECORD
